love_equinox/__init__.py
love_equinox-0.2.2.dist-info/METADATA
love_equinox-0.2.2.dist-info/WHEEL
love_equinox-0.2.2.dist-info/top_level.txt
love_equinox-0.2.2.dist-info/RECORD
